{"nodes": [{"id": "c_engineering_final_year_project_manasarthi_backend_src_controllers_moodcontroller_ts", "label": "moodController.ts", "file_type": "code", "source_file": "C:\\Engineering\\Final Year Project\\ManaSarathi\\backend\\src\\controllers\\moodController.ts", "source_location": "L1"}, {"id": "moodcontroller_normalizelegacymood", "label": "normalizeLegacyMood()", "file_type": "code", "source_file": "C:\\Engineering\\Final Year Project\\ManaSarathi\\backend\\src\\controllers\\moodController.ts", "source_location": "L39"}, {"id": "moodcontroller_getmoodentries", "label": "getMoodEntries()", "file_type": "code", "source_file": "C:\\Engineering\\Final Year Project\\ManaSarathi\\backend\\src\\controllers\\moodController.ts", "source_location": "L65"}, {"id": "moodcontroller_createmoodentry", "label": "createMoodEntry()", "file_type": "code", "source_file": "C:\\Engineering\\Final Year Project\\ManaSarathi\\backend\\src\\controllers\\moodController.ts", "source_location": "L99"}, {"id": "moodcontroller_deletemoodentry", "label": "deleteMoodEntry()", "file_type": "code", "source_file": "C:\\Engineering\\Final Year Project\\ManaSarathi\\backend\\src\\controllers\\moodController.ts", "source_location": "L154"}, {"id": "moodcontroller_getmoodstats", "label": "getMoodStats()", "file_type": "code", "source_file": "C:\\Engineering\\Final Year Project\\ManaSarathi\\backend\\src\\controllers\\moodController.ts", "source_location": "L185"}], "edges": [{"source": "c_engineering_final_year_project_manasarthi_backend_src_controllers_moodcontroller_ts", "target": "express", "relation": "imports_from", "confidence": "EXTRACTED", "source_file": "C:\\Engineering\\Final Year Project\\ManaSarathi\\backend\\src\\controllers\\moodController.ts", "source_location": "L1", "weight": 1.0}, {"source": "c_engineering_final_year_project_manasarthi_backend_src_controllers_moodcontroller_ts", "target": "c_engineering_final_year_project_manasarthi_backend_src_config_database", "relation": "imports_from", "confidence": "EXTRACTED", "source_file": "C:\\Engineering\\Final Year Project\\ManaSarathi\\backend\\src\\controllers\\moodController.ts", "source_location": "L2", "weight": 1.0}, {"source": "c_engineering_final_year_project_manasarthi_backend_src_controllers_moodcontroller_ts", "target": "moodcontroller_normalizelegacymood", "relation": "contains", "confidence": "EXTRACTED", "source_file": "C:\\Engineering\\Final Year Project\\ManaSarathi\\backend\\src\\controllers\\moodController.ts", "source_location": "L39", "weight": 1.0}, {"source": "c_engineering_final_year_project_manasarthi_backend_src_controllers_moodcontroller_ts", "target": "moodcontroller_getmoodentries", "relation": "contains", "confidence": "EXTRACTED", "source_file": "C:\\Engineering\\Final Year Project\\ManaSarathi\\backend\\src\\controllers\\moodController.ts", "source_location": "L65", "weight": 1.0}, {"source": "c_engineering_final_year_project_manasarthi_backend_src_controllers_moodcontroller_ts", "target": "moodcontroller_createmoodentry", "relation": "contains", "confidence": "EXTRACTED", "source_file": "C:\\Engineering\\Final Year Project\\ManaSarathi\\backend\\src\\controllers\\moodController.ts", "source_location": "L99", "weight": 1.0}, {"source": "c_engineering_final_year_project_manasarthi_backend_src_controllers_moodcontroller_ts", "target": "moodcontroller_deletemoodentry", "relation": "contains", "confidence": "EXTRACTED", "source_file": "C:\\Engineering\\Final Year Project\\ManaSarathi\\backend\\src\\controllers\\moodController.ts", "source_location": "L154", "weight": 1.0}, {"source": "c_engineering_final_year_project_manasarthi_backend_src_controllers_moodcontroller_ts", "target": "moodcontroller_getmoodstats", "relation": "contains", "confidence": "EXTRACTED", "source_file": "C:\\Engineering\\Final Year Project\\ManaSarathi\\backend\\src\\controllers\\moodController.ts", "source_location": "L185", "weight": 1.0}, {"source": "moodcontroller_createmoodentry", "target": "moodcontroller_normalizelegacymood", "relation": "calls", "confidence": "EXTRACTED", "source_file": "C:\\Engineering\\Final Year Project\\ManaSarathi\\backend\\src\\controllers\\moodController.ts", "source_location": "L108", "weight": 1.0}], "raw_calls": [{"caller_nid": "moodcontroller_normalizelegacymood", "callee": "trim", "source_file": "C:\\Engineering\\Final Year Project\\ManaSarathi\\backend\\src\\controllers\\moodController.ts", "source_location": "L44"}, {"caller_nid": "moodcontroller_normalizelegacymood", "callee": "trim", "source_file": "C:\\Engineering\\Final Year Project\\ManaSarathi\\backend\\src\\controllers\\moodController.ts", "source_location": "L45"}, {"caller_nid": "moodcontroller_normalizelegacymood", "callee": "toLowerCase", "source_file": "C:\\Engineering\\Final Year Project\\ManaSarathi\\backend\\src\\controllers\\moodController.ts", "source_location": "L48"}, {"caller_nid": "moodcontroller_normalizelegacymood", "callee": "trim", "source_file": "C:\\Engineering\\Final Year Project\\ManaSarathi\\backend\\src\\controllers\\moodController.ts", "source_location": "L48"}, {"caller_nid": "moodcontroller_normalizelegacymood", "callee": "toLowerCase", "source_file": "C:\\Engineering\\Final Year Project\\ManaSarathi\\backend\\src\\controllers\\moodController.ts", "source_location": "L53"}, {"caller_nid": "moodcontroller_normalizelegacymood", "callee": "trim", "source_file": "C:\\Engineering\\Final Year Project\\ManaSarathi\\backend\\src\\controllers\\moodController.ts", "source_location": "L53"}, {"caller_nid": "moodcontroller_getmoodentries", "callee": "json", "source_file": "C:\\Engineering\\Final Year Project\\ManaSarathi\\backend\\src\\controllers\\moodController.ts", "source_location": "L69"}, {"caller_nid": "moodcontroller_getmoodentries", "callee": "status", "source_file": "C:\\Engineering\\Final Year Project\\ManaSarathi\\backend\\src\\controllers\\moodController.ts", "source_location": "L69"}, {"caller_nid": "moodcontroller_getmoodentries", "callee": "findMany", "source_file": "C:\\Engineering\\Final Year Project\\ManaSarathi\\backend\\src\\controllers\\moodController.ts", "source_location": "L82"}, {"caller_nid": "moodcontroller_getmoodentries", "callee": "min", "source_file": "C:\\Engineering\\Final Year Project\\ManaSarathi\\backend\\src\\controllers\\moodController.ts", "source_location": "L85"}, {"caller_nid": "moodcontroller_getmoodentries", "callee": "parseInt", "source_file": "C:\\Engineering\\Final Year Project\\ManaSarathi\\backend\\src\\controllers\\moodController.ts", "source_location": "L85"}, {"caller_nid": "moodcontroller_getmoodentries", "callee": "json", "source_file": "C:\\Engineering\\Final Year Project\\ManaSarathi\\backend\\src\\controllers\\moodController.ts", "source_location": "L88"}, {"caller_nid": "moodcontroller_getmoodentries", "callee": "error", "source_file": "C:\\Engineering\\Final Year Project\\ManaSarathi\\backend\\src\\controllers\\moodController.ts", "source_location": "L90"}, {"caller_nid": "moodcontroller_getmoodentries", "callee": "json", "source_file": "C:\\Engineering\\Final Year Project\\ManaSarathi\\backend\\src\\controllers\\moodController.ts", "source_location": "L91"}, {"caller_nid": "moodcontroller_getmoodentries", "callee": "status", "source_file": "C:\\Engineering\\Final Year Project\\ManaSarathi\\backend\\src\\controllers\\moodController.ts", "source_location": "L91"}, {"caller_nid": "moodcontroller_createmoodentry", "callee": "json", "source_file": "C:\\Engineering\\Final Year Project\\ManaSarathi\\backend\\src\\controllers\\moodController.ts", "source_location": "L103"}, {"caller_nid": "moodcontroller_createmoodentry", "callee": "status", "source_file": "C:\\Engineering\\Final Year Project\\ManaSarathi\\backend\\src\\controllers\\moodController.ts", "source_location": "L103"}, {"caller_nid": "moodcontroller_createmoodentry", "callee": "json", "source_file": "C:\\Engineering\\Final Year Project\\ManaSarathi\\backend\\src\\controllers\\moodController.ts", "source_location": "L111"}, {"caller_nid": "moodcontroller_createmoodentry", "callee": "status", "source_file": "C:\\Engineering\\Final Year Project\\ManaSarathi\\backend\\src\\controllers\\moodController.ts", "source_location": "L111"}, {"caller_nid": "moodcontroller_createmoodentry", "callee": "toLowerCase", "source_file": "C:\\Engineering\\Final Year Project\\ManaSarathi\\backend\\src\\controllers\\moodController.ts", "source_location": "L118"}, {"caller_nid": "moodcontroller_createmoodentry", "callee": "trim", "source_file": "C:\\Engineering\\Final Year Project\\ManaSarathi\\backend\\src\\controllers\\moodController.ts", "source_location": "L118"}, {"caller_nid": "moodcontroller_createmoodentry", "callee": "toLowerCase", "source_file": "C:\\Engineering\\Final Year Project\\ManaSarathi\\backend\\src\\controllers\\moodController.ts", "source_location": "L120"}, {"caller_nid": "moodcontroller_createmoodentry", "callee": "trim", "source_file": "C:\\Engineering\\Final Year Project\\ManaSarathi\\backend\\src\\controllers\\moodController.ts", "source_location": "L120"}, {"caller_nid": "moodcontroller_createmoodentry", "callee": "trim", "source_file": "C:\\Engineering\\Final Year Project\\ManaSarathi\\backend\\src\\controllers\\moodController.ts", "source_location": "L121"}, {"caller_nid": "moodcontroller_createmoodentry", "callee": "trim", "source_file": "C:\\Engineering\\Final Year Project\\ManaSarathi\\backend\\src\\controllers\\moodController.ts", "source_location": "L122"}, {"caller_nid": "moodcontroller_createmoodentry", "callee": "trim", "source_file": "C:\\Engineering\\Final Year Project\\ManaSarathi\\backend\\src\\controllers\\moodController.ts", "source_location": "L124"}, {"caller_nid": "moodcontroller_createmoodentry", "callee": "trim", "source_file": "C:\\Engineering\\Final Year Project\\ManaSarathi\\backend\\src\\controllers\\moodController.ts", "source_location": "L125"}, {"caller_nid": "moodcontroller_createmoodentry", "callee": "max", "source_file": "C:\\Engineering\\Final Year Project\\ManaSarathi\\backend\\src\\controllers\\moodController.ts", "source_location": "L128"}, {"caller_nid": "moodcontroller_createmoodentry", "callee": "min", "source_file": "C:\\Engineering\\Final Year Project\\ManaSarathi\\backend\\src\\controllers\\moodController.ts", "source_location": "L128"}, {"caller_nid": "moodcontroller_createmoodentry", "callee": "round", "source_file": "C:\\Engineering\\Final Year Project\\ManaSarathi\\backend\\src\\controllers\\moodController.ts", "source_location": "L128"}, {"caller_nid": "moodcontroller_createmoodentry", "callee": "create", "source_file": "C:\\Engineering\\Final Year Project\\ManaSarathi\\backend\\src\\controllers\\moodController.ts", "source_location": "L131"}, {"caller_nid": "moodcontroller_createmoodentry", "callee": "json", "source_file": "C:\\Engineering\\Final Year Project\\ManaSarathi\\backend\\src\\controllers\\moodController.ts", "source_location": "L143"}, {"caller_nid": "moodcontroller_createmoodentry", "callee": "status", "source_file": "C:\\Engineering\\Final Year Project\\ManaSarathi\\backend\\src\\controllers\\moodController.ts", "source_location": "L143"}, {"caller_nid": "moodcontroller_createmoodentry", "callee": "error", "source_file": "C:\\Engineering\\Final Year Project\\ManaSarathi\\backend\\src\\controllers\\moodController.ts", "source_location": "L145"}, {"caller_nid": "moodcontroller_createmoodentry", "callee": "json", "source_file": "C:\\Engineering\\Final Year Project\\ManaSarathi\\backend\\src\\controllers\\moodController.ts", "source_location": "L146"}, {"caller_nid": "moodcontroller_createmoodentry", "callee": "status", "source_file": "C:\\Engineering\\Final Year Project\\ManaSarathi\\backend\\src\\controllers\\moodController.ts", "source_location": "L146"}, {"caller_nid": "moodcontroller_deletemoodentry", "callee": "json", "source_file": "C:\\Engineering\\Final Year Project\\ManaSarathi\\backend\\src\\controllers\\moodController.ts", "source_location": "L158"}, {"caller_nid": "moodcontroller_deletemoodentry", "callee": "status", "source_file": "C:\\Engineering\\Final Year Project\\ManaSarathi\\backend\\src\\controllers\\moodController.ts", "source_location": "L158"}, {"caller_nid": "moodcontroller_deletemoodentry", "callee": "findFirst", "source_file": "C:\\Engineering\\Final Year Project\\ManaSarathi\\backend\\src\\controllers\\moodController.ts", "source_location": "L164"}, {"caller_nid": "moodcontroller_deletemoodentry", "callee": "json", "source_file": "C:\\Engineering\\Final Year Project\\ManaSarathi\\backend\\src\\controllers\\moodController.ts", "source_location": "L169"}, {"caller_nid": "moodcontroller_deletemoodentry", "callee": "status", "source_file": "C:\\Engineering\\Final Year Project\\ManaSarathi\\backend\\src\\controllers\\moodController.ts", "source_location": "L169"}, {"caller_nid": "moodcontroller_deletemoodentry", "callee": "delete", "source_file": "C:\\Engineering\\Final Year Project\\ManaSarathi\\backend\\src\\controllers\\moodController.ts", "source_location": "L172"}, {"caller_nid": "moodcontroller_deletemoodentry", "callee": "json", "source_file": "C:\\Engineering\\Final Year Project\\ManaSarathi\\backend\\src\\controllers\\moodController.ts", "source_location": "L174"}, {"caller_nid": "moodcontroller_deletemoodentry", "callee": "error", "source_file": "C:\\Engineering\\Final Year Project\\ManaSarathi\\backend\\src\\controllers\\moodController.ts", "source_location": "L176"}, {"caller_nid": "moodcontroller_deletemoodentry", "callee": "json", "source_file": "C:\\Engineering\\Final Year Project\\ManaSarathi\\backend\\src\\controllers\\moodController.ts", "source_location": "L177"}, {"caller_nid": "moodcontroller_deletemoodentry", "callee": "status", "source_file": "C:\\Engineering\\Final Year Project\\ManaSarathi\\backend\\src\\controllers\\moodController.ts", "source_location": "L177"}, {"caller_nid": "moodcontroller_getmoodstats", "callee": "json", "source_file": "C:\\Engineering\\Final Year Project\\ManaSarathi\\backend\\src\\controllers\\moodController.ts", "source_location": "L189"}, {"caller_nid": "moodcontroller_getmoodstats", "callee": "status", "source_file": "C:\\Engineering\\Final Year Project\\ManaSarathi\\backend\\src\\controllers\\moodController.ts", "source_location": "L189"}, {"caller_nid": "moodcontroller_getmoodstats", "callee": "min", "source_file": "C:\\Engineering\\Final Year Project\\ManaSarathi\\backend\\src\\controllers\\moodController.ts", "source_location": "L193"}, {"caller_nid": "moodcontroller_getmoodstats", "callee": "parseInt", "source_file": "C:\\Engineering\\Final Year Project\\ManaSarathi\\backend\\src\\controllers\\moodController.ts", "source_location": "L193"}, {"caller_nid": "moodcontroller_getmoodstats", "callee": "setDate", "source_file": "C:\\Engineering\\Final Year Project\\ManaSarathi\\backend\\src\\controllers\\moodController.ts", "source_location": "L195"}, {"caller_nid": "moodcontroller_getmoodstats", "callee": "getDate", "source_file": "C:\\Engineering\\Final Year Project\\ManaSarathi\\backend\\src\\controllers\\moodController.ts", "source_location": "L195"}, {"caller_nid": "moodcontroller_getmoodstats", "callee": "findMany", "source_file": "C:\\Engineering\\Final Year Project\\ManaSarathi\\backend\\src\\controllers\\moodController.ts", "source_location": "L198"}, {"caller_nid": "moodcontroller_getmoodstats", "callee": "forEach", "source_file": "C:\\Engineering\\Final Year Project\\ManaSarathi\\backend\\src\\controllers\\moodController.ts", "source_location": "L208"}, {"caller_nid": "moodcontroller_getmoodstats", "callee": "setHours", "source_file": "C:\\Engineering\\Final Year Project\\ManaSarathi\\backend\\src\\controllers\\moodController.ts", "source_location": "L215"}, {"caller_nid": "moodcontroller_getmoodstats", "callee": "map", "source_file": "C:\\Engineering\\Final Year Project\\ManaSarathi\\backend\\src\\controllers\\moodController.ts", "source_location": "L218"}, {"caller_nid": "moodcontroller_getmoodstats", "callee": "setDate", "source_file": "C:\\Engineering\\Final Year Project\\ManaSarathi\\backend\\src\\controllers\\moodController.ts", "source_location": "L227"}, {"caller_nid": "moodcontroller_getmoodstats", "callee": "getDate", "source_file": "C:\\Engineering\\Final Year Project\\ManaSarathi\\backend\\src\\controllers\\moodController.ts", "source_location": "L227"}, {"caller_nid": "moodcontroller_getmoodstats", "callee": "has", "source_file": "C:\\Engineering\\Final Year Project\\ManaSarathi\\backend\\src\\controllers\\moodController.ts", "source_location": "L228"}, {"caller_nid": "moodcontroller_getmoodstats", "callee": "toISOString", "source_file": "C:\\Engineering\\Final Year Project\\ManaSarathi\\backend\\src\\controllers\\moodController.ts", "source_location": "L228"}, {"caller_nid": "moodcontroller_getmoodstats", "callee": "toFixed", "source_file": "C:\\Engineering\\Final Year Project\\ManaSarathi\\backend\\src\\controllers\\moodController.ts", "source_location": "L237"}, {"caller_nid": "moodcontroller_getmoodstats", "callee": "sort", "source_file": "C:\\Engineering\\Final Year Project\\ManaSarathi\\backend\\src\\controllers\\moodController.ts", "source_location": "L240"}, {"caller_nid": "moodcontroller_getmoodstats", "callee": "entries", "source_file": "C:\\Engineering\\Final Year Project\\ManaSarathi\\backend\\src\\controllers\\moodController.ts", "source_location": "L240"}, {"caller_nid": "moodcontroller_getmoodstats", "callee": "json", "source_file": "C:\\Engineering\\Final Year Project\\ManaSarathi\\backend\\src\\controllers\\moodController.ts", "source_location": "L243"}, {"caller_nid": "moodcontroller_getmoodstats", "callee": "toISOString", "source_file": "C:\\Engineering\\Final Year Project\\ManaSarathi\\backend\\src\\controllers\\moodController.ts", "source_location": "L246"}, {"caller_nid": "moodcontroller_getmoodstats", "callee": "toISOString", "source_file": "C:\\Engineering\\Final Year Project\\ManaSarathi\\backend\\src\\controllers\\moodController.ts", "source_location": "L246"}, {"caller_nid": "moodcontroller_getmoodstats", "callee": "error", "source_file": "C:\\Engineering\\Final Year Project\\ManaSarathi\\backend\\src\\controllers\\moodController.ts", "source_location": "L255"}, {"caller_nid": "moodcontroller_getmoodstats", "callee": "json", "source_file": "C:\\Engineering\\Final Year Project\\ManaSarathi\\backend\\src\\controllers\\moodController.ts", "source_location": "L256"}, {"caller_nid": "moodcontroller_getmoodstats", "callee": "status", "source_file": "C:\\Engineering\\Final Year Project\\ManaSarathi\\backend\\src\\controllers\\moodController.ts", "source_location": "L256"}]}