{"nodes": [{"id": "c_engineering_final_year_project_maansarathi_frontend_scripts_generate_tailwind_compat_mjs", "label": "generate-tailwind-compat.mjs", "file_type": "code", "source_file": "C:\\Engineering\\Final Year Project\\MaanSarathi\\frontend\\scripts\\generate-tailwind-compat.mjs", "source_location": "L1"}, {"id": "generate_tailwind_compat_walk", "label": "walk()", "file_type": "code", "source_file": "C:\\Engineering\\Final Year Project\\MaanSarathi\\frontend\\scripts\\generate-tailwind-compat.mjs", "source_location": "L12"}, {"id": "generate_tailwind_compat_escapeclassselector", "label": "escapeClassSelector()", "file_type": "code", "source_file": "C:\\Engineering\\Final Year Project\\MaanSarathi\\frontend\\scripts\\generate-tailwind-compat.mjs", "source_location": "L50"}, {"id": "generate_tailwind_compat_escaperegex", "label": "escapeRegex()", "file_type": "code", "source_file": "C:\\Engineering\\Final Year Project\\MaanSarathi\\frontend\\scripts\\generate-tailwind-compat.mjs", "source_location": "L52"}, {"id": "generate_tailwind_compat_parseutilityclass", "label": "parseUtilityClass()", "file_type": "code", "source_file": "C:\\Engineering\\Final Year Project\\MaanSarathi\\frontend\\scripts\\generate-tailwind-compat.mjs", "source_location": "L112"}, {"id": "generate_tailwind_compat_resolvecolorvalue", "label": "resolveColorValue()", "file_type": "code", "source_file": "C:\\Engineering\\Final Year Project\\MaanSarathi\\frontend\\scripts\\generate-tailwind-compat.mjs", "source_location": "L206"}, {"id": "generate_tailwind_compat_buildselector", "label": "buildSelector()", "file_type": "code", "source_file": "C:\\Engineering\\Final Year Project\\MaanSarathi\\frontend\\scripts\\generate-tailwind-compat.mjs", "source_location": "L226"}, {"id": "generate_tailwind_compat_builddeclaration", "label": "buildDeclaration()", "file_type": "code", "source_file": "C:\\Engineering\\Final Year Project\\MaanSarathi\\frontend\\scripts\\generate-tailwind-compat.mjs", "source_location": "L235"}, {"id": "generate_tailwind_compat_buildgradientstopvalue", "label": "buildGradientStopValue()", "file_type": "code", "source_file": "C:\\Engineering\\Final Year Project\\MaanSarathi\\frontend\\scripts\\generate-tailwind-compat.mjs", "source_location": "L243"}, {"id": "generate_tailwind_compat_buildgradientstopdeclaration", "label": "buildGradientStopDeclaration()", "file_type": "code", "source_file": "C:\\Engineering\\Final Year Project\\MaanSarathi\\frontend\\scripts\\generate-tailwind-compat.mjs", "source_location": "L251"}], "edges": [{"source": "c_engineering_final_year_project_maansarathi_frontend_scripts_generate_tailwind_compat_mjs", "target": "node_fs", "relation": "imports_from", "confidence": "EXTRACTED", "source_file": "C:\\Engineering\\Final Year Project\\MaanSarathi\\frontend\\scripts\\generate-tailwind-compat.mjs", "source_location": "L1", "weight": 1.0}, {"source": "c_engineering_final_year_project_maansarathi_frontend_scripts_generate_tailwind_compat_mjs", "target": "node_path", "relation": "imports_from", "confidence": "EXTRACTED", "source_file": "C:\\Engineering\\Final Year Project\\MaanSarathi\\frontend\\scripts\\generate-tailwind-compat.mjs", "source_location": "L2", "weight": 1.0}, {"source": "c_engineering_final_year_project_maansarathi_frontend_scripts_generate_tailwind_compat_mjs", "target": "node_url", "relation": "imports_from", "confidence": "EXTRACTED", "source_file": "C:\\Engineering\\Final Year Project\\MaanSarathi\\frontend\\scripts\\generate-tailwind-compat.mjs", "source_location": "L3", "weight": 1.0}, {"source": "c_engineering_final_year_project_maansarathi_frontend_scripts_generate_tailwind_compat_mjs", "target": "generate_tailwind_compat_walk", "relation": "contains", "confidence": "EXTRACTED", "source_file": "C:\\Engineering\\Final Year Project\\MaanSarathi\\frontend\\scripts\\generate-tailwind-compat.mjs", "source_location": "L12", "weight": 1.0}, {"source": "c_engineering_final_year_project_maansarathi_frontend_scripts_generate_tailwind_compat_mjs", "target": "generate_tailwind_compat_escapeclassselector", "relation": "contains", "confidence": "EXTRACTED", "source_file": "C:\\Engineering\\Final Year Project\\MaanSarathi\\frontend\\scripts\\generate-tailwind-compat.mjs", "source_location": "L50", "weight": 1.0}, {"source": "c_engineering_final_year_project_maansarathi_frontend_scripts_generate_tailwind_compat_mjs", "target": "generate_tailwind_compat_escaperegex", "relation": "contains", "confidence": "EXTRACTED", "source_file": "C:\\Engineering\\Final Year Project\\MaanSarathi\\frontend\\scripts\\generate-tailwind-compat.mjs", "source_location": "L52", "weight": 1.0}, {"source": "c_engineering_final_year_project_maansarathi_frontend_scripts_generate_tailwind_compat_mjs", "target": "generate_tailwind_compat_parseutilityclass", "relation": "contains", "confidence": "EXTRACTED", "source_file": "C:\\Engineering\\Final Year Project\\MaanSarathi\\frontend\\scripts\\generate-tailwind-compat.mjs", "source_location": "L112", "weight": 1.0}, {"source": "c_engineering_final_year_project_maansarathi_frontend_scripts_generate_tailwind_compat_mjs", "target": "generate_tailwind_compat_resolvecolorvalue", "relation": "contains", "confidence": "EXTRACTED", "source_file": "C:\\Engineering\\Final Year Project\\MaanSarathi\\frontend\\scripts\\generate-tailwind-compat.mjs", "source_location": "L206", "weight": 1.0}, {"source": "c_engineering_final_year_project_maansarathi_frontend_scripts_generate_tailwind_compat_mjs", "target": "generate_tailwind_compat_buildselector", "relation": "contains", "confidence": "EXTRACTED", "source_file": "C:\\Engineering\\Final Year Project\\MaanSarathi\\frontend\\scripts\\generate-tailwind-compat.mjs", "source_location": "L226", "weight": 1.0}, {"source": "c_engineering_final_year_project_maansarathi_frontend_scripts_generate_tailwind_compat_mjs", "target": "generate_tailwind_compat_builddeclaration", "relation": "contains", "confidence": "EXTRACTED", "source_file": "C:\\Engineering\\Final Year Project\\MaanSarathi\\frontend\\scripts\\generate-tailwind-compat.mjs", "source_location": "L235", "weight": 1.0}, {"source": "c_engineering_final_year_project_maansarathi_frontend_scripts_generate_tailwind_compat_mjs", "target": "generate_tailwind_compat_buildgradientstopvalue", "relation": "contains", "confidence": "EXTRACTED", "source_file": "C:\\Engineering\\Final Year Project\\MaanSarathi\\frontend\\scripts\\generate-tailwind-compat.mjs", "source_location": "L243", "weight": 1.0}, {"source": "c_engineering_final_year_project_maansarathi_frontend_scripts_generate_tailwind_compat_mjs", "target": "generate_tailwind_compat_buildgradientstopdeclaration", "relation": "contains", "confidence": "EXTRACTED", "source_file": "C:\\Engineering\\Final Year Project\\MaanSarathi\\frontend\\scripts\\generate-tailwind-compat.mjs", "source_location": "L251", "weight": 1.0}, {"source": "generate_tailwind_compat_buildselector", "target": "generate_tailwind_compat_escapeclassselector", "relation": "calls", "confidence": "EXTRACTED", "source_file": "C:\\Engineering\\Final Year Project\\MaanSarathi\\frontend\\scripts\\generate-tailwind-compat.mjs", "source_location": "L227", "weight": 1.0}], "raw_calls": [{"caller_nid": "generate_tailwind_compat_walk", "callee": "readdirSync", "source_file": "C:\\Engineering\\Final Year Project\\MaanSarathi\\frontend\\scripts\\generate-tailwind-compat.mjs", "source_location": "L13"}, {"caller_nid": "generate_tailwind_compat_walk", "callee": "join", "source_file": "C:\\Engineering\\Final Year Project\\MaanSarathi\\frontend\\scripts\\generate-tailwind-compat.mjs", "source_location": "L14"}, {"caller_nid": "generate_tailwind_compat_walk", "callee": "isDirectory", "source_file": "C:\\Engineering\\Final Year Project\\MaanSarathi\\frontend\\scripts\\generate-tailwind-compat.mjs", "source_location": "L15"}, {"caller_nid": "generate_tailwind_compat_walk", "callee": "test", "source_file": "C:\\Engineering\\Final Year Project\\MaanSarathi\\frontend\\scripts\\generate-tailwind-compat.mjs", "source_location": "L20"}, {"caller_nid": "generate_tailwind_compat_walk", "callee": "push", "source_file": "C:\\Engineering\\Final Year Project\\MaanSarathi\\frontend\\scripts\\generate-tailwind-compat.mjs", "source_location": "L21"}, {"caller_nid": "generate_tailwind_compat_escapeclassselector", "callee": "replaceAll", "source_file": "C:\\Engineering\\Final Year Project\\MaanSarathi\\frontend\\scripts\\generate-tailwind-compat.mjs", "source_location": "L50"}, {"caller_nid": "generate_tailwind_compat_escapeclassselector", "callee": "replaceAll", "source_file": "C:\\Engineering\\Final Year Project\\MaanSarathi\\frontend\\scripts\\generate-tailwind-compat.mjs", "source_location": "L50"}, {"caller_nid": "generate_tailwind_compat_escaperegex", "callee": "replace", "source_file": "C:\\Engineering\\Final Year Project\\MaanSarathi\\frontend\\scripts\\generate-tailwind-compat.mjs", "source_location": "L52"}, {"caller_nid": "generate_tailwind_compat_parseutilityclass", "callee": "match", "source_file": "C:\\Engineering\\Final Year Project\\MaanSarathi\\frontend\\scripts\\generate-tailwind-compat.mjs", "source_location": "L113"}, {"caller_nid": "generate_tailwind_compat_parseutilityclass", "callee": "match", "source_file": "C:\\Engineering\\Final Year Project\\MaanSarathi\\frontend\\scripts\\generate-tailwind-compat.mjs", "source_location": "L139"}, {"caller_nid": "generate_tailwind_compat_parseutilityclass", "callee": "max", "source_file": "C:\\Engineering\\Final Year Project\\MaanSarathi\\frontend\\scripts\\generate-tailwind-compat.mjs", "source_location": "L142"}, {"caller_nid": "generate_tailwind_compat_parseutilityclass", "callee": "min", "source_file": "C:\\Engineering\\Final Year Project\\MaanSarathi\\frontend\\scripts\\generate-tailwind-compat.mjs", "source_location": "L142"}, {"caller_nid": "generate_tailwind_compat_parseutilityclass", "callee": "Number", "source_file": "C:\\Engineering\\Final Year Project\\MaanSarathi\\frontend\\scripts\\generate-tailwind-compat.mjs", "source_location": "L142"}, {"caller_nid": "generate_tailwind_compat_parseutilityclass", "callee": "match", "source_file": "C:\\Engineering\\Final Year Project\\MaanSarathi\\frontend\\scripts\\generate-tailwind-compat.mjs", "source_location": "L153"}, {"caller_nid": "generate_tailwind_compat_parseutilityclass", "callee": "test", "source_file": "C:\\Engineering\\Final Year Project\\MaanSarathi\\frontend\\scripts\\generate-tailwind-compat.mjs", "source_location": "L163"}, {"caller_nid": "generate_tailwind_compat_parseutilityclass", "callee": "Number", "source_file": "C:\\Engineering\\Final Year Project\\MaanSarathi\\frontend\\scripts\\generate-tailwind-compat.mjs", "source_location": "L164"}, {"caller_nid": "generate_tailwind_compat_parseutilityclass", "callee": "max", "source_file": "C:\\Engineering\\Final Year Project\\MaanSarathi\\frontend\\scripts\\generate-tailwind-compat.mjs", "source_location": "L175"}, {"caller_nid": "generate_tailwind_compat_parseutilityclass", "callee": "min", "source_file": "C:\\Engineering\\Final Year Project\\MaanSarathi\\frontend\\scripts\\generate-tailwind-compat.mjs", "source_location": "L175"}, {"caller_nid": "generate_tailwind_compat_parseutilityclass", "callee": "Number", "source_file": "C:\\Engineering\\Final Year Project\\MaanSarathi\\frontend\\scripts\\generate-tailwind-compat.mjs", "source_location": "L175"}, {"caller_nid": "generate_tailwind_compat_parseutilityclass", "callee": "match", "source_file": "C:\\Engineering\\Final Year Project\\MaanSarathi\\frontend\\scripts\\generate-tailwind-compat.mjs", "source_location": "L185"}, {"caller_nid": "generate_tailwind_compat_parseutilityclass", "callee": "max", "source_file": "C:\\Engineering\\Final Year Project\\MaanSarathi\\frontend\\scripts\\generate-tailwind-compat.mjs", "source_location": "L195"}, {"caller_nid": "generate_tailwind_compat_parseutilityclass", "callee": "min", "source_file": "C:\\Engineering\\Final Year Project\\MaanSarathi\\frontend\\scripts\\generate-tailwind-compat.mjs", "source_location": "L195"}, {"caller_nid": "generate_tailwind_compat_parseutilityclass", "callee": "Number", "source_file": "C:\\Engineering\\Final Year Project\\MaanSarathi\\frontend\\scripts\\generate-tailwind-compat.mjs", "source_location": "L195"}, {"caller_nid": "generate_tailwind_compat_resolvecolorvalue", "callee": "match", "source_file": "C:\\Engineering\\Final Year Project\\MaanSarathi\\frontend\\scripts\\generate-tailwind-compat.mjs", "source_location": "L211"}, {"caller_nid": "generate_tailwind_compat_resolvecolorvalue", "callee": "has", "source_file": "C:\\Engineering\\Final Year Project\\MaanSarathi\\frontend\\scripts\\generate-tailwind-compat.mjs", "source_location": "L219"}]}